make_django/__init__.py
make_django/__main__.py
make_django/main.py
make_django/batteries/__init__.py
make_django/batteries/__pycache__/__init__.cpython-37.pyc
make_django/batteries/rest/__init__.py
make_django/batteries/rest/settings.py
make_django/batteries/rest/__pycache__/__init__.cpython-37.pyc
make_django/batteries/rest/data/app/serializers.py
make_django/batteries/rest/data/app/tests/test_rest_api.py
make_django/batteries/sass/__init__.py
make_django/batteries/sass/settings.py
make_django/batteries/sass/__pycache__/__init__.cpython-37.pyc
make_django/batteries/sass/data/app/static/css/base.sass
make_django/batteries/sass/data/app/static/css/index.sass
make_django/batteries/sass/data/app/templates/base.html
make_django/batteries/sass/data/app/templates/index.html
make_django/data/pip.cmd
make_django/data/python.cmd
make_django/data/app/urls.py
make_django/data/app/views.py
make_django/data/app/static/favicon.ico
make_django/data/app/static/css/base.css
make_django/data/app/static/css/index.css
make_django/data/app/templates/base.html
make_django/data/app/templates/index.html
make_django/data/app/tests/__init__.py
make_django/data/app/tests/test_models.py
make_django/data/app/tests/test_views.py
make_django/data/application/settings.py
make_django/data/application/settings/__init__.py
make_django/data/application/settings/main.py
make_django/data/application/templatetags/__init__.py
make_django/data/application/templatetags/filters.py
make_django/data/tests/__init__.py
make_django-0.0.1.4.dist-info/METADATA
make_django-0.0.1.4.dist-info/WHEEL
make_django-0.0.1.4.dist-info/top_level.txt
make_django-0.0.1.4.dist-info/RECORD
