Metadata-Version: 2.1
Name: make-django
Version: 0.0.1.4
Summary: Tool for rapid making django projects
Home-page: UNKNOWN
Author: filantus
Author-email: filantus@mail.ru
License: GPL
Platform: UNKNOWN
Classifier: Intended Audience :: Developers
Classifier: License :: OSI Approved :: GNU General Public License (GPL)
Classifier: Programming Language :: Python :: 3.5
Classifier: Operating System :: OS Independent
Requires-Dist: virtualenv
Requires-Dist: redbaron
